visionx/__init__.py
visionx/config.py
visionx/server.py
visionx/api/__init__.py
visionx/api/vision_api.py
visionx/dbnet_crnn/__init__.py
visionx/dbnet_crnn/image_text.py
visionx/dbnet_crnn/modelv1.1/det/model
visionx/dbnet_crnn/modelv1.1/det/params
visionx/dbnet_crnn/modelv1.1/rec/model
visionx/dbnet_crnn/modelv1.1/rec/params
visionx/dbnet_crnn/ppocr/__init__.py
visionx/dbnet_crnn/ppocr/db_post_process.py
visionx/dbnet_crnn/ppocr/db_process.py
visionx/dbnet_crnn/ppocr/utils/__init__.py
visionx/dbnet_crnn/ppocr/utils/character.py
visionx/dbnet_crnn/ppocr/utils/keys.txt
visionx/dbnet_crnn/tools/__init__.py
visionx/dbnet_crnn/tools/predict_det.py
visionx/dbnet_crnn/tools/predict_rec.py
visionx/dbnet_crnn/tools/utility.py
visionx/service/__init__.py
visionx/service/image_diff.py
visionx/service/image_infer.py
visionx/service/image_merge.py
visionx/service/image_similar.py
visionx/service/image_text.py
visionx/service/image_trace.py
visionx/service/image_utils.py
visionx-1.0.1.dist-info/LICENSE
visionx-1.0.1.dist-info/METADATA
visionx-1.0.1.dist-info/WHEEL
visionx-1.0.1.dist-info/entry_points.txt
visionx-1.0.1.dist-info/top_level.txt
visionx-1.0.1.dist-info/RECORD
