Metadata-Version: 2.1
Name: visionx
Version: 1.0.1
Summary: Video UI analysis tool!
Home-page: https://github.com/openutx
Author: lijiawei
Author-email: jiawei.li2@qq.com
License: Apache License 2.0
Keywords: vision,utx,yolox,diff,ui,tools
Platform: any
Classifier: Development Status :: 5 - Production/Stable
Classifier: Environment :: Console :: Curses
Classifier: Operating System :: MacOS
Classifier: Operating System :: POSIX
Classifier: Operating System :: Microsoft :: Windows
Classifier: Programming Language :: Python :: 3 :: Only
Classifier: Programming Language :: Python :: 3.6
Classifier: Programming Language :: Python :: 3.7
Classifier: Programming Language :: Python :: 3.8
Classifier: Programming Language :: Python :: 3.9
Classifier: Programming Language :: Python :: Implementation :: CPython
License-File: LICENSE
Requires-Dist: Flask
Requires-Dist: Flask-Cors
Requires-Dist: scipy
Requires-Dist: numpy
Requires-Dist: opencv-python (==4.5.2.52)
Requires-Dist: pillow (==9.0.1)
Requires-Dist: paddlepaddle (==2.2.2)
Requires-Dist: gunicorn (==20.0.4)
Requires-Dist: onnxruntime (==1.10.0)
Requires-Dist: pyclipper (==1.2.0)
Requires-Dist: shapely (==1.7.1)
Requires-Dist: protobuf (==3.20.2)
